terminal_table/__init__.py
terminal_table/terminal_table.py
terminal_table-2.0.1.dist-info/LICENSE.txt
terminal_table-2.0.1.dist-info/WHEEL
terminal_table-2.0.1.dist-info/METADATA
terminal_table-2.0.1.dist-info/RECORD
